shadowjourney/__init__.py
shadowjourney/exceptions.py
shadowjourney/shadowjourney.py
shadowjourney-0.1.9.dist-info/LICENSE
shadowjourney-0.1.9.dist-info/METADATA
shadowjourney-0.1.9.dist-info/WHEEL
shadowjourney-0.1.9.dist-info/top_level.txt
shadowjourney-0.1.9.dist-info/RECORD
