Metadata-Version: 2.1
Name: shadowjourney
Version: 0.1.9
Summary: shadowjourney API wrapper and cool stuff
Home-page: https://github.com/shadowjourneyy/shadowjourney
Author: Ichate
Author-email: ichate_@outlook.com
Classifier: Programming Language :: Python :: 3
Classifier: License :: OSI Approved :: MIT License
Classifier: Operating System :: OS Independent
Requires-Python: >=3.6
License-File: LICENSE
Requires-Dist: requests
